{
  "exported_at": "2026-05-11T13:09:16Z",
  "id": 71,
  "model": "ir.cron",
  "payload": {
    "active": true,
    "code": "model._cron_auto_check_out()",
    "interval_number": 4,
    "interval_type": "hours",
    "model_id": [
      842,
      "Attendance"
    ],
    "name": "Attendance: Automatically check-out employees",
    "user_id": [
      1,
      "BICC"
    ]
  },
  "payload_sha256": "c1d1553bd7aa6f0db77d5dd6eecd7513a8c4d69c9934b82993eba7afec986da9",
  "write_date": "2025-12-09 02:58:04",
  "xml_id": "hr_attendance.hr_attendance_check_out_cron"
}
