<kanban class="o_kanban_mobile">
                    <templates>
                        <t t-name="card">
                            <div class="row mb4">
                                <div class="col-6">
                                    <field class="fw-bolder" name="name"/>
                                </div>
                                <div class="col-6 text-end">
                                    <field class="badge rounded-pill" name="type_tax_use"/>
                                    <field class="badge rounded-pill" name="tax_scope"/>
                                </div>
                            </div>
                            <field class="text-muted" name="description"/>
                        </t>
                    </templates>
                </kanban>