{
  "exported_at": "2026-05-11T13:09:06Z",
  "id": 711,
  "lookup": {
    "active": true,
    "inherit_id": 138,
    "inherit_id_display": "res.partner.bank.form",
    "key": false,
    "mode": "primary",
    "name": "res.partner.bank.form.inherit.account",
    "type": "form",
    "website_id": false
  },
  "model": "ir.ui.view",
  "payload_sha256": "e16bc7997461051c879af55c462c78d0c166051c33ab1acd4b9d477a2efb5234",
  "write_date": "2025-12-09 02:56:39",
  "xml_id": "account.view_partner_bank_form_inherit_account"
}
