<search string="Search Journal Items">
                    <field name="name" string="Journal Item" filter_domain="[                         '|', '|', '|',                         ('name', 'ilike', self), ('ref', 'ilike', self), ('account_id', 'ilike', self), ('partner_id', 'ilike', self)]"/>
                    <field name="name"/>
                    <field name="move_id"/>
                    <field name="ref"/>
                    <field name="payment_date"/>
                    <field name="partner_id"/>
                    <field name="journal_id"/>
                    <field name="currency_id" groups="base.group_multi_currency" invisible="1"/>
                    <field name="company_currency_id" invisible="1"/>
                    <separator/>
                    <filter string="Posted" name="posted" domain="[('parent_state', '=', 'posted')]" help="Posted Journal Items" invisible="1"/>
                    <separator/>
                    <filter string="Invoices" name="invoices" domain="[('amount_residual', '&gt;', '0')]" invisible="context.get('journal_type') != 'sale'"/>
                    <filter string="Credit Notes" name="credit_notes" domain="[('amount_residual', '&lt;', '0')]" invisible="context.get('journal_type') != 'sale'"/>
                    <filter string="Bills" name="bills" domain="[('amount_residual', '&lt;', '0')]" invisible="context.get('journal_type') != 'purchase'"/>
                    <filter string="Refunds" name="refunds" domain="[('amount_residual', '&gt;', '0')]" invisible="context.get('journal_type') != 'purchase'"/>
                    <separator/>
                    <filter string="Invoice Date" name="invoice_date" date="invoice_date"/>
                    <filter string="Next Payment Date" name="payment_date" date="payment_date"/>
                    <filter string="Overdue" name="late" domain="[('date_maturity', '&lt;', 'today')]" help="Overdue payments, due date passed"/>
                    <filter string="Early Discount" name="early_discount" domain="[('discount_date', '!=', False), ('discount_date', '&gt;', 'today')]"/>
                    <separator/>
                    <filter string="Report Dates" name="date_between" domain="[('date', '&gt;=', context.get('date_from')), ('date', '&lt;=', context.get('date_to'))]" invisible="1"/>
                    <filter string="Report Dates" name="date_before" domain="[('date', '&lt;=', context.get('date_to'))]" invisible="1"/>
                    <separator/>
                    <group>
                        <filter string="Currency" name="group_by_currencies" domain="[]" context="{'group_by': 'currency_id'}"/>
                        <filter string="Partner" name="group_by_partner" domain="[]" context="{'group_by': 'partner_id'}"/>
                        <filter string="Journal" name="journal" domain="[]" context="{'group_by': 'journal_id'}"/>
                        <filter string="Invoice Date" name="groupby_invoice_date" domain="[]" context="{'group_by': 'invoice_date'}"/>
                        <filter string="Next Payment Date" name="groupby_payment_date" domain="[]" context="{'group_by': 'payment_date'}"/>
                    </group>
                </search>