{
  "exported_at": "2026-05-11T13:09:07Z",
  "id": 6219,
  "lookup": {
    "active": true,
    "inherit_id": 893,
    "inherit_id_display": "pdf_export_main",
    "key": "account_reports.pdf_export_main_customer_report",
    "mode": "primary",
    "name": "pdf_export_main_customer_report",
    "type": "qweb",
    "website_id": false
  },
  "model": "ir.ui.view",
  "payload_sha256": "4d87dc9cd7636f6f80924c828836e091f321993d1ef16fa154a672979b31ab27",
  "write_date": "2025-12-09 02:59:10",
  "xml_id": "account_reports.pdf_export_main_customer_report"
}
