<kanban>
                <templates>
                    <t t-name="card">
                        <field name="name" class="fw-bolder" string="Name"/>
                        <div class="d-flex flex-column">
                            <field name="interface_key"/>
                            <field name="focused_models"/>
                            <div class="d-flex gap-2 align-items-center mt-2">
                                <field name="ai_agent" widget="many2one_avatar"/>
                                <field name="ai_agent"/>
                            </div>
                        </div>
                    </t>
                </templates>
            </kanban>