<form string="Client Action">
                    <sheet>
                        <group>
                            <group name="main_details">
                                <field name="name"/>
                                <field name="xml_id" string="External ID"/>
                                <field name="binding_type"/>
                                <field name="tag"/>
                            </group>
                            <group name="action_details">
                                <field name="type" readonly="1"/>
                                <field name="target"/>
                                <field name="context"/>
                            </group>
                        </group>
                        <group name="help" string="Help">
                            <field name="help" nolabel="1" class="oe-bordered-editor"/>
                        </group>
                    </sheet>
                </form>