{
  "exported_at": "2026-05-11T13:09:07Z",
  "id": 6165,
  "lookup": {
    "active": true,
    "inherit_id": 6114,
    "inherit_id_display": "documents.sharing.view.form",
    "key": false,
    "mode": "extension",
    "name": "documents.sharing.view.form.inherit.documents",
    "type": "form",
    "website_id": false
  },
  "model": "ir.ui.view",
  "payload_sha256": "b0609aa0ffc21e4e4c731f38aa58a7b211e902d8ca0d38b2af4e5f53590c4b89",
  "write_date": "2025-12-09 02:58:00",
  "xml_id": "documents_spreadsheet.documents_sharing_view_form"
}
