<list create="false" multi_edit="1" decoration-info="shortcut_document_id" default_order="is_folder, create_date DESC, id DESC">
                <field name="is_favorited" widget="document_favorite" nolabel="1"/>
                <field name="type" width="25px" widget="documents_type_icon" nolabel="1"/>
                <field name="name" required="True" readonly="False"/>
                <field name="folder_id" optional="show"/>
                <field name="user_folder_id" column_invisible="True"/>
                <field name="user_can_move" column_invisible="True"/>
                <field name="display_name" column_invisible="1"/>
                <field name="owner_id" widget="many2one_avatar_user" optional="show"/>
                <field name="partner_id" optional="show"/>
                <field name="tag_ids" widget="many2many_tags" optional="hide" options="{'color_field': 'color'}"/>
                <field name="url" optional="hide"/>
                <field name="lock_uid" groups="base.group_user" optional="hide"/>
                <field name="company_id" groups="base.group_multi_company" optional="hide"/>
                <field name="available_embedded_actions_ids" optional="hide" widget="many2many_tags" groups="base.group_user"/>
                <field name="create_date" optional="hide"/>
                <field name="write_date" optional="show"/>
                <field name="file_extension" optional="hide"/>
                <field name="file_size" optional="show" widget="document_size"/>
                <field name="res_id" string="Link to" optional="hide"/>
                <field name="id" column_invisible="1"/>
                <field name="access_token" column_invisible="1"/>
                <field name="active" column_invisible="1"/>
                <field name="user_permission" column_invisible="1"/>
                <field name="attachment_id" column_invisible="1"/>
                <field name="res_model" column_invisible="1"/>
                <field name="res_model_name" column_invisible="1"/>
                <field name="res_name" column_invisible="1"/>
                <field name="shortcut_document_id" column_invisible="1"/>
                <field name="mimetype" column_invisible="1"/>
                <field name="access_url" column_invisible="1"/>
                <field name="alias_email" groups="base.group_user" optional="hide" widget="email"/>
                <field name="alias_name" column_invisible="1"/>
                <field name="alias_domain_id" column_invisible="1"/>
                <field name="alias_tag_ids" widget="many2many_tags" options="{'color_field': 'color'}" column_invisible="1"/> <!-- fetch `color` too -->
                <field name="create_activity_type_id" column_invisible="1"/>
                <field name="create_activity_user_id" column_invisible="1"/>
                <widget name="documents_list_actions" width="125px"/>
            </list>