{
  "exported_at": "2026-05-11T13:09:07Z",
  "id": 4758,
  "lookup": {
    "active": true,
    "inherit_id": 1192,
    "inherit_id_display": "project.task.burndown.chart.report.view.search",
    "key": false,
    "mode": "extension",
    "name": "project.task.burndown.chart.report.view.search.fsm",
    "type": "search",
    "website_id": false
  },
  "model": "ir.ui.view",
  "payload_sha256": "311e645f78d3e8df8b107f4c1006931255703e6fcef5f80a69389f67faf3750b",
  "write_date": "2025-12-09 03:00:33",
  "xml_id": "industry_fsm_report.project_task_burndown_chart_report_view_search_fsm"
}
