<t name="Payment Methods" t-name="payment.payment_methods">
        <t t-call="portal.frontend_layout">
            <t t-set="page_title">Payment Methods</t>
            <t t-set="additional_title"><t t-esc="page_title"/></t>
            <div class="wrap">
                <div class="container">
                    <!-- Portal breadcrumb -->
                    <t t-call="payment.portal_breadcrumb"/>
                    <!-- Payment methods page -->
                    <div class="row justify-content-center">
                        <div class="col-lg-7">
                            <t t-call="payment.form"/>
                        </div>
                    </div>
                </div>
            </div>
        </t>
    </t>