<form string="Confirmation">
                <p>People invited to collaborate on the project will have portal access rights.</p>
                <p>They can edit shared project tasks and view specific documents in read mode on your website. This includes leads/opportunities, quotations/sales orders, purchase orders, invoices and bills, timesheets, and tickets.</p>
                <p>You have full control and can revoke portal access anytime. Are you ready to proceed?</p>
                <footer>
                    <button string="Grant Portal Access" name="action_send_mail" type="object" class="btn-primary" data-hotkey="q"/>
                    <button string="Discard" class="btn-secondary" special="cancel" data-hotkey="x"/>
                </footer>
            </form>