{
  "exported_at": "2026-05-11T13:09:06Z",
  "id": 1602,
  "lookup": {
    "active": true,
    "inherit_id": 1551,
    "inherit_id_display": "Expense split",
    "key": false,
    "mode": "extension",
    "name": "hr.expense.split.view.inherit.sale.expense",
    "type": "form",
    "website_id": false
  },
  "model": "ir.ui.view",
  "payload_sha256": "85d2075db5b3a8ffc12c4f427e3c98a4efdc34e350eb5e13ce52c539e062301f",
  "write_date": "2025-12-09 03:00:29",
  "xml_id": "sale_expense.hr_expense_split_view_inherit_sale_expense"
}
