<search string="Stock Moves">
                <field name="location_id" string="Location" filter_domain="['|',('location_id', 'ilike', self),('location_dest_id', 'ilike', self)]" groups="stock.group_stock_multi_locations"/>
                <field name="product_id"/>
                <field name="picking_id" string="Transfer"/>
                <field name="reference" string="Reference"/>
                <field name="product_category_name" string="Category"/>
                <field name="lot_id" string="Lot/Serial Number" groups="stock.group_production_lot"/>
                <field name="package_id" string="Source Package" groups="stock.group_tracking_lot"/>
                <field name="result_package_id" string="Destination Package" groups="stock.group_tracking_lot"/>
                <field name="owner_id" string="Owner" groups="stock.group_tracking_owner"/>
                <separator/>
                <filter string="To Do" name="todo" domain="[('state', 'not in', ['done', 'draft', 'cancel'])]"/>
                <filter string="Done" name="done" domain="[('state', '=', 'done')]"/>
                <separator/>
                <filter string="Incoming" name="incoming" domain="[('picking_id.picking_type_id.code', '=', 'incoming')]"/>
                <filter string="Outgoing" name="outgoing" domain="[('picking_id.picking_type_id.code', '=', 'outgoing')]"/>
                <filter string="Internal" name="internal" domain="[('picking_id.picking_type_id.code', '=', 'internal')]"/>
                <filter string="Manufacturing" name="manufacturing" domain="[('picking_id.picking_type_id.code', '=', 'mrp_operation')]" invisible="1"/>
                <separator/>
                <filter name="date" date="date" default_period="month"/>
                <filter string="Last 30 Days" name="filter_last_30_days" domain="[('date','&gt;=', 'today -30d')]"/>
                <filter string="Last 3 Months" name="filter_last_3_months" domain="[('date','&gt;=', 'today -3m')]"/>
                <filter string="Last 12 Months" name="filter_last_12_months" domain="[('date','&gt;=', 'today -12m')]"/>
                <separator/>
                <filter string="Inventory Adjustments" name="inventory" domain="[('is_inventory', '=', True)]"/>
                <separator/>
                <group name="groupby">
                    <filter string="Product" name="groupby_product_id" domain="[]" context="{'group_by': 'product_id'}"/>
                    <filter string="Status" name="by_state" domain="[]" context="{'group_by': 'state'}"/>
                    <filter string="Date" name="by_date" domain="[]" context="{'group_by': 'date'}"/>
                    <filter string="Transfers" name="by_picking" domain="[]" context="{'group_by': 'picking_id'}"/>
                    <filter string="Location" name="by_location" domain="[]" context="{'group_by': 'location_id'}"/>
                    <filter string="Category" name="by_category" domain="[]" context="{'group_by': 'product_category_name'}"/>
                </group>
            </search>