<data inherit_id="appointment.appointment_progress_bar">
        <xpath expr="//a[contains(@t-att-class, 'step==STEP_TIME')]" position="before">
            <t t-set="is_manual_assign_user_resource_first" t-value="not appointment_type.is_auto_assign and not appointment_type.is_date_first"/>
            <t t-set="STEP_OPERATOR_SELECT" t-value="10"/>
            <t t-set="show_operator_select" t-value="step==STEP_OPERATOR_SELECT or is_manual_assign_user_resource_first and len(users_or_resources_possible) &gt; 1"/>
            <t t-if="show_operator_select">
                <li class="d-flex align-items-center">
                    <a t-att-class="'text-decoration-none text-truncate ' + (step==STEP_OPERATOR_SELECT and 'fw-bold text-reset cursor-default' or step&gt;STEP_OPERATOR_SELECT and ' ' or 'cursor-default text-muted')" t-att-href="'#' if step&lt;STEP_OPERATOR_SELECT or step==STEP_OPERATOR_SELECT else '/appointment/%s?%s' % (appointment_type.id, keep_query('filter_appointment_type_ids', 'filter_resource_ids', 'filter_staff_user_ids', 'invite_token'))">
                        <span t-if="appointment_type.schedule_based_on == 'users'">Operator</span>
                        <span t-else="">Meeting</span>
                    </a>
                    <span class="d-inline-block mx-sm-3 fa fa-angle-right text-muted fs-5"/>
                </li>
            </t>
        </xpath>
    </data>