{
  "exported_at": "2026-05-10T12:35:50Z",
  "id": 2027,
  "model": "ir.model.access",
  "payload": {
    "group_id": [
      1,
      "Internal User"
    ],
    "model_id": [
      910,
      "Gamification User Badge"
    ],
    "name": "Badge-user Employee",
    "perm_create": true,
    "perm_read": true,
    "perm_unlink": true,
    "perm_write": true
  },
  "payload_sha256": "d4303bc120099389436a61d18ce67dbbe8491f2a51e173d835cb62f0f9d94477",
  "write_date": "2025-12-09 02:58:08",
  "xml_id": "hr_gamification.badge_base_user"
}
