{
  "exported_at": "2026-05-10T12:35:50Z",
  "id": 2028,
  "model": "ir.model.access",
  "payload": {
    "group_id": [
      1,
      "Internal User"
    ],
    "model_id": [
      3474,
      "Employee Certification Report"
    ],
    "name": "hr.employee.certification.report",
    "perm_create": false,
    "perm_read": true,
    "perm_unlink": false,
    "perm_write": false
  },
  "payload_sha256": "59a326db81bed0583eaca2bdfb02d0459cbcef5abee512ed06f96a87608791a7",
  "write_date": "2025-12-09 02:58:28",
  "xml_id": "hr_skills.access_hr_employee_certification_report_user"
}
