{
  "exported_at": "2026-05-10T12:35:50Z",
  "id": 1595,
  "model": "ir.model.access",
  "payload": {
    "group_id": [
      41,
      "Project / Administrator"
    ],
    "model_id": [
      1062,
      "Worksheet Template"
    ],
    "name": "access_project_worksheet_template_manager",
    "perm_create": true,
    "perm_read": true,
    "perm_unlink": true,
    "perm_write": true
  },
  "payload_sha256": "da187899e98143abef9d0ec700b774d98cfdae5837a16cc4d79f3c6046f5c0e9",
  "write_date": "2025-12-09 03:00:33",
  "xml_id": "industry_fsm_report.access_project_worksheet_template_manager"
}
