{
  "exported_at": "2026-05-10T12:35:50Z",
  "id": 1855,
  "model": "ir.model.access",
  "payload": {
    "group_id": [
      148,
      "eLearning / Officer"
    ],
    "model_id": [
      1511,
      "Course"
    ],
    "name": "slide.channel.officer",
    "perm_create": true,
    "perm_read": true,
    "perm_unlink": false,
    "perm_write": true
  },
  "payload_sha256": "36989984467229526a0f88dd3f2bf515867177777d7c9ba3880ae308d13f137e",
  "write_date": "2026-01-28 12:01:25",
  "xml_id": "website_slides.access_slide_channel_officer"
}
