{
  "exported_at": "2026-05-11T13:09:27Z",
  "id": 4904,
  "model": "ir.model.fields",
  "payload": {
    "field_description": "Financial Accounts Prefixes",
    "model_id": [
      343,
      "Analytic Plan's Applicabilities"
    ],
    "name": "account_prefix",
    "relation": false,
    "required": false,
    "state": "base",
    "store": true,
    "translate": false,
    "ttype": "char"
  },
  "payload_sha256": "83dc2ef9a3e0f3646b7a2bc36f973dc38da404c8a9fceec53e7ab30bbfaf8b93",
  "write_date": "",
  "xml_id": "account.field_account_analytic_applicability__account_prefix"
}
