{
  "exported_at": "2026-05-10T12:35:48Z",
  "id": 28905,
  "model": "ir.model.fields",
  "payload": {
    "field_description": "Date From",
    "model_id": [
      3564,
      "Accounting Return"
    ],
    "name": "date_from",
    "relation": false,
    "required": true,
    "state": "base",
    "store": true,
    "translate": false,
    "ttype": "date"
  },
  "payload_sha256": "b6ee9571c17178b70c9bf4371e78edc953fcfbc9871736f23fa0188e8dd0403d",
  "write_date": "",
  "xml_id": "account_reports.field_account_return__date_from"
}
