{
  "exported_at": "2026-05-11T13:09:27Z",
  "id": 5078,
  "model": "ir.model.fields",
  "payload": {
    "field_description": "Active",
    "model_id": [
      446,
      "Incoterms"
    ],
    "name": "active",
    "relation": false,
    "required": false,
    "state": "base",
    "store": true,
    "translate": false,
    "ttype": "boolean"
  },
  "payload_sha256": "1c1804497e4f3759561ceb9d883b71e09cf364d0ab866bf4f139483a48300e57",
  "write_date": "",
  "xml_id": "account.field_account_incoterms__active"
}
