{
  "exported_at": "2026-05-10T12:35:46Z",
  "id": 5952,
  "model": "ir.model.fields",
  "payload": {
    "field_description": "Created on",
    "model_id": [
      494,
      "Bank Connection"
    ],
    "name": "create_date",
    "relation": false,
    "required": false,
    "state": "base",
    "store": true,
    "translate": false,
    "ttype": "datetime"
  },
  "payload_sha256": "3b060d92d92e299abf346dcaa8c1759dbb9d44e1fe730c480cc43f9edbc379f5",
  "write_date": "",
  "xml_id": "account_online_synchronization.field_account_online_link__create_date"
}
