{
  "exported_at": "2026-05-10T12:35:48Z",
  "id": 27472,
  "model": "ir.model.fields",
  "payload": {
    "field_description": "Account Move Count",
    "model_id": [
      85,
      "Contact"
    ],
    "name": "account_move_count",
    "relation": false,
    "required": false,
    "state": "base",
    "store": false,
    "translate": false,
    "ttype": "integer"
  },
  "payload_sha256": "63549a19023795e4bf403c31ab34370c13efb6e0b25493e52c54df1fa3934b75",
  "write_date": "",
  "xml_id": "account.field_res_partner__account_move_count"
}
