{
  "exported_at": "2026-05-10T12:35:46Z",
  "id": 4030,
  "model": "ir.model.fields",
  "payload": {
    "field_description": "Access warning",
    "model_id": [
      425,
      "Journal"
    ],
    "name": "access_warning",
    "relation": false,
    "required": false,
    "state": "base",
    "store": false,
    "translate": false,
    "ttype": "text"
  },
  "payload_sha256": "3da7d7b6e22340e7a0313b076e0239c3ae22a56087eaed02da140f0696599b56",
  "write_date": "",
  "xml_id": "account.field_account_journal__access_warning"
}
