{
  "exported_at": "2026-05-10T12:35:47Z",
  "id": 15226,
  "model": "ir.model.fields",
  "payload": {
    "field_description": "Avatar 128",
    "model_id": [
      939,
      "Appointment Resource"
    ],
    "name": "avatar_128",
    "relation": false,
    "required": false,
    "state": "base",
    "store": false,
    "translate": false,
    "ttype": "binary"
  },
  "payload_sha256": "a91e7cfd9121b2f626f98428c5128e59d18d678ec40169aa7daa50ac88eb2c29",
  "write_date": "",
  "xml_id": "appointment.field_appointment_resource__avatar_128"
}
