{
  "exported_at": "2026-05-11T13:09:28Z",
  "id": 12177,
  "model": "ir.model.fields",
  "payload": {
    "field_description": "Required",
    "model_id": [
      786,
      "Approver"
    ],
    "name": "required",
    "relation": false,
    "required": false,
    "state": "base",
    "store": true,
    "translate": false,
    "ttype": "boolean"
  },
  "payload_sha256": "f84eb075f55569c0c3d888f08d23de7121d0649f1f07fde26db4d2bbc6034625",
  "write_date": "",
  "xml_id": "approvals.field_approval_approver__required"
}
