{
  "exported_at": "2026-05-10T12:35:48Z",
  "id": 19397,
  "model": "ir.model.fields",
  "payload": {
    "field_description": "Active Parent Id",
    "model_id": [
      1110,
      "Embedded Actions"
    ],
    "name": "parent_res_id",
    "relation": false,
    "required": false,
    "state": "base",
    "store": true,
    "translate": false,
    "ttype": "integer"
  },
  "payload_sha256": "2afdc57c0f8195078eefae70a417fe700db25041462a584f1300f78b66a41a5e",
  "write_date": "",
  "xml_id": "base.field_ir_embedded_actions__parent_res_id"
}
