{
  "exported_at": "2026-05-11T13:09:29Z",
  "id": 26769,
  "model": "ir.model.fields",
  "payload": {
    "field_description": "Display Name",
    "model_id": [
      2829,
      "Properties Base Definition Mixin"
    ],
    "name": "display_name",
    "relation": false,
    "required": false,
    "state": "base",
    "store": false,
    "translate": false,
    "ttype": "char"
  },
  "payload_sha256": "230727de3dfeb256aa13d44bebbd4fe17fdaea90940c946c3e77a31c5ffcf0c2",
  "write_date": "",
  "xml_id": "base.field_properties_base_definition_mixin__display_name"
}
