{
  "exported_at": "2026-05-10T12:35:46Z",
  "id": 561,
  "model": "ir.model.fields",
  "payload": {
    "field_description": "Value",
    "model_id": [
      37,
      "System Parameter"
    ],
    "name": "value",
    "relation": false,
    "required": true,
    "state": "base",
    "store": true,
    "translate": false,
    "ttype": "text"
  },
  "payload_sha256": "bcafdd1d45e3ac1e95aab71c3da35b4c78737d1aae95de57cd3a5d7c339bd75c",
  "write_date": "",
  "xml_id": "base.field_ir_config_parameter__value"
}
