{
  "exported_at": "2026-05-11T13:09:26Z",
  "id": 810,
  "model": "ir.model.fields",
  "payload": {
    "field_description": "State Name",
    "model_id": [
      80,
      "Country state"
    ],
    "name": "name",
    "relation": false,
    "required": true,
    "state": "base",
    "store": true,
    "translate": false,
    "ttype": "char"
  },
  "payload_sha256": "d8bdecb28fddc5f961e893991aa28c0493b2f69a702d5668555ff6410cb0642c",
  "write_date": "",
  "xml_id": "base.field_res_country_state__name"
}
