{
  "exported_at": "2026-05-11T13:09:26Z",
  "id": 1093,
  "model": "ir.model.fields",
  "payload": {
    "field_description": "Last Updated on",
    "model_id": [
      96,
      "Users Log"
    ],
    "name": "write_date",
    "relation": false,
    "required": false,
    "state": "base",
    "store": true,
    "translate": false,
    "ttype": "datetime"
  },
  "payload_sha256": "59066be7688a518737d1ac5ef9bf3d67eb35a730a08fd9b766f7df0762d2c2d7",
  "write_date": "",
  "xml_id": "base.field_res_users_log__write_date"
}
