{
  "exported_at": "2026-05-11T13:09:28Z",
  "id": 14971,
  "model": "ir.model.fields",
  "payload": {
    "field_description": "Name",
    "model_id": [
      925,
      "Recycling Model"
    ],
    "name": "name",
    "relation": false,
    "required": true,
    "state": "base",
    "store": true,
    "translate": false,
    "ttype": "char"
  },
  "payload_sha256": "5f032ed30951cc71434b3b984dfee483591830bac5b9ebbecd8ef1567d9ea248",
  "write_date": "",
  "xml_id": "data_recycle.field_data_recycle_model__name"
}
