{
  "exported_at": "2026-05-10T12:35:48Z",
  "id": 29465,
  "model": "ir.model.fields",
  "payload": {
    "field_description": "From",
    "model_id": [
      822,
      "Payslip Worked Days"
    ],
    "name": "date_from",
    "relation": false,
    "required": false,
    "state": "base",
    "store": true,
    "translate": false,
    "ttype": "date"
  },
  "payload_sha256": "a6b4062d8536d523b20e3380c6f2b185ff711f489a634002503f9ddeacfb037e",
  "write_date": "",
  "xml_id": "hr_payroll.field_hr_payslip_worked_days__date_from"
}
