{
  "exported_at": "2026-05-11T13:09:29Z",
  "id": 29514,
  "model": "ir.model.fields",
  "payload": {
    "field_description": "Created on",
    "model_id": [
      3708,
      "Salary Input Section"
    ],
    "name": "create_date",
    "relation": false,
    "required": false,
    "state": "base",
    "store": true,
    "translate": false,
    "ttype": "datetime"
  },
  "payload_sha256": "3028d29873fe68ba684c91b84610a9412bb2a19857402dc1410012b33c2f552a",
  "write_date": "",
  "xml_id": "hr_payroll.field_hr_salary_rule_section__create_date"
}
