{
  "exported_at": "2026-05-11T13:09:29Z",
  "id": 28579,
  "model": "ir.model.fields",
  "payload": {
    "field_description": "Levels Count",
    "model_id": [
      644,
      "Skill Type"
    ],
    "name": "levels_count",
    "relation": false,
    "required": false,
    "state": "base",
    "store": true,
    "translate": false,
    "ttype": "integer"
  },
  "payload_sha256": "ab8d93b3525a8f4af5478e4dc0daaec36b5f4aa0f70470d9c00550f03ac86172",
  "write_date": "",
  "xml_id": "hr_skills.field_hr_skill_type__levels_count"
}
