{
  "exported_at": "2026-05-10T12:35:48Z",
  "id": 28607,
  "model": "ir.model.fields",
  "payload": {
    "field_description": "Working Time",
    "model_id": [
      812,
      "HR Work Entry Type"
    ],
    "name": "is_work",
    "relation": false,
    "required": false,
    "state": "base",
    "store": false,
    "translate": false,
    "ttype": "boolean"
  },
  "payload_sha256": "2aebe6f2ecb4280ecf96df92c53b151951b0e0896c1dde99b50ec85d774df854",
  "write_date": "",
  "xml_id": "hr_work_entry.field_hr_work_entry_type__is_work"
}
