{
  "exported_at": "2026-05-10T12:35:48Z",
  "id": 27071,
  "model": "ir.model.fields",
  "payload": {
    "field_description": "Offline since",
    "model_id": [
      205,
      "Guest"
    ],
    "name": "offline_since",
    "relation": false,
    "required": false,
    "state": "base",
    "store": false,
    "translate": false,
    "ttype": "datetime"
  },
  "payload_sha256": "e9650658a818441fed0b61163569153cf75185dde4887ba205d1f5cfaf7f8ffc",
  "write_date": "",
  "xml_id": "mail.field_mail_guest__offline_since"
}
