{
  "exported_at": "2026-05-10T12:35:47Z",
  "id": 18182,
  "model": "ir.model.fields",
  "payload": {
    "field_description": "Archive",
    "model_id": [
      1041,
      "Maintenance Request"
    ],
    "name": "archive",
    "relation": false,
    "required": false,
    "state": "base",
    "store": true,
    "translate": false,
    "ttype": "boolean"
  },
  "payload_sha256": "1eacdeaacc08ecedf3b8e01dc10a8d4127582e6feb51d6902c4db8363426a7bb",
  "write_date": "",
  "xml_id": "maintenance.field_maintenance_request__archive"
}
