{
  "exported_at": "2026-05-10T12:35:47Z",
  "id": 14131,
  "model": "ir.model.fields",
  "payload": {
    "field_description": "Mass Mailings",
    "model_id": [
      891,
      "Mailing List"
    ],
    "name": "mailing_ids",
    "relation": "mailing.mailing",
    "required": false,
    "state": "base",
    "store": true,
    "translate": false,
    "ttype": "many2many"
  },
  "payload_sha256": "635093c7529c9883325c6e46393479c1950777cb73b35d6ff77e985c173fbc07",
  "write_date": "",
  "xml_id": "mass_mailing.field_mailing_list__mailing_ids"
}
