{
  "exported_at": "2026-05-10T12:35:48Z",
  "id": 20202,
  "model": "ir.model.fields",
  "payload": {
    "field_description": "Has Message",
    "model_id": [
      963,
      "Work Center Usage"
    ],
    "name": "has_message",
    "relation": false,
    "required": false,
    "state": "base",
    "store": false,
    "translate": false,
    "ttype": "boolean"
  },
  "payload_sha256": "4a39d465815dd3f980272d2f111ebb4835d5eb62ff12dbb713d8022787485fc0",
  "write_date": "",
  "xml_id": "mrp.field_mrp_routing_workcenter__has_message"
}
