{
  "exported_at": "2026-05-11T13:09:29Z",
  "id": 19994,
  "model": "ir.model.fields",
  "payload": {
    "field_description": "ID",
    "model_id": [
      1185,
      "Project Sharing Collaborator Wizard"
    ],
    "name": "id",
    "relation": false,
    "required": false,
    "state": "base",
    "store": true,
    "translate": false,
    "ttype": "integer"
  },
  "payload_sha256": "86642d1383c5880d0cb4bf7daaf710510859b9c6efb43e0fbe358b72046fe254",
  "write_date": "",
  "xml_id": "project.field_project_share_collaborator_wizard__id"
}
