{
  "exported_at": "2026-05-11T13:09:27Z",
  "id": 7952,
  "model": "ir.model.fields",
  "payload": {
    "field_description": "# Tasks",
    "model_id": [
      85,
      "Contact"
    ],
    "name": "task_count",
    "relation": false,
    "required": false,
    "state": "base",
    "store": false,
    "translate": false,
    "ttype": "integer"
  },
  "payload_sha256": "9ccde4b18e54640b33744f3b9e819792d0cd35edc60db443f97193ff9dba4f76",
  "write_date": "",
  "xml_id": "project.field_res_partner__task_count"
}
