{
  "exported_at": "2026-05-11T13:09:27Z",
  "id": 7543,
  "model": "ir.model.fields",
  "payload": {
    "field_description": "Action Needed",
    "model_id": [
      594,
      "Rating Mixin"
    ],
    "name": "message_needaction",
    "relation": false,
    "required": false,
    "state": "base",
    "store": false,
    "translate": false,
    "ttype": "boolean"
  },
  "payload_sha256": "6ba58ec818faa5d713e479aa87b0dc2a00303c85280d0cdfdbb553ae76af6dfb",
  "write_date": "",
  "xml_id": "rating.field_rating_mixin__message_needaction"
}
