{
  "exported_at": "2026-05-11T13:09:26Z",
  "id": 3040,
  "model": "ir.model.fields",
  "payload": {
    "field_description": "ID",
    "model_id": [
      361,
      "Product Attribute Custom Value"
    ],
    "name": "id",
    "relation": false,
    "required": false,
    "state": "base",
    "store": true,
    "translate": false,
    "ttype": "integer"
  },
  "payload_sha256": "2b6935e4eae0d928b44ff9673b8ec42f30e7441891423398407539e2286f573d",
  "write_date": "",
  "xml_id": "sale.field_product_attribute_custom_value__id"
}
