{
  "exported_at": "2026-05-11T13:09:27Z",
  "id": 5251,
  "model": "ir.model.fields",
  "payload": {
    "field_description": "Display Name",
    "model_id": [
      455,
      "Account Move Reversal"
    ],
    "name": "display_name",
    "relation": false,
    "required": false,
    "state": "base",
    "store": false,
    "translate": false,
    "ttype": "char"
  },
  "payload_sha256": "d928014cf13423e0d942b39ac98669cc4b365e8a65548cf2a99314d58a2c99ae",
  "write_date": "",
  "xml_id": "sale_timesheet.field_account_move_reversal__display_name"
}
