{
  "exported_at": "2026-05-10T12:35:47Z",
  "id": 12014,
  "model": "ir.model.fields",
  "payload": {
    "field_description": "Incoterm",
    "model_id": [
      613,
      "Sales Order"
    ],
    "name": "incoterm",
    "relation": "account.incoterms",
    "required": false,
    "state": "base",
    "store": true,
    "translate": false,
    "ttype": "many2one"
  },
  "payload_sha256": "704375efd8b33a8c274baa54e3d70dff5f336bbb1e886e58868ead92ace0941e",
  "write_date": "",
  "xml_id": "sale_stock.field_sale_order__incoterm"
}
