{
  "exported_at": "2026-05-11T13:09:29Z",
  "id": 29682,
  "model": "ir.model.fields",
  "payload": {
    "field_description": "Billable",
    "model_id": [
      3334,
      "Project Template create Wizard"
    ],
    "name": "allow_billable",
    "relation": false,
    "required": false,
    "state": "base",
    "store": false,
    "translate": false,
    "ttype": "boolean"
  },
  "payload_sha256": "31b04be2a4670888f2cf286d090012570a9616ee39b15fb250342e4ae2582fa2",
  "write_date": "",
  "xml_id": "sale_project.field_project_template_create_wizard__allow_billable"
}
