{
  "exported_at": "2026-05-11T13:09:29Z",
  "id": 21837,
  "model": "ir.model.fields",
  "payload": {
    "field_description": "Display Name",
    "model_id": [
      1358,
      "SMS Account Sender Name Wizard"
    ],
    "name": "display_name",
    "relation": false,
    "required": false,
    "state": "base",
    "store": false,
    "translate": false,
    "ttype": "char"
  },
  "payload_sha256": "a13a092fa21f0a6cd1a76e728f374a8eef4f7ae3141b47529a89abd17eb0b370",
  "write_date": "",
  "xml_id": "sms.field_sms_account_sender__display_name"
}
