{
  "exported_at": "2026-05-11T13:09:28Z",
  "id": 17807,
  "model": "ir.model.fields",
  "payload": {
    "field_description": "Facebook Access Token",
    "model_id": [
      1024,
      "Social Account"
    ],
    "name": "facebook_access_token",
    "relation": false,
    "required": false,
    "state": "base",
    "store": true,
    "translate": false,
    "ttype": "char"
  },
  "payload_sha256": "ed2dc03381e111f79c95f37ec217bebf0b3d23340a9411ab021629a83cb91df4",
  "write_date": "",
  "xml_id": "social_facebook.field_social_account__facebook_access_token"
}
