{
  "exported_at": "2026-05-11T13:09:27Z",
  "id": 10998,
  "model": "ir.model.fields",
  "payload": {
    "field_description": "Display Name",
    "model_id": [
      729,
      "Stock Move"
    ],
    "name": "display_name",
    "relation": false,
    "required": false,
    "state": "base",
    "store": false,
    "translate": false,
    "ttype": "char"
  },
  "payload_sha256": "2223939ef88267d0e56e5d90421389f5ad59904c9e292113c05049dcfb3902cb",
  "write_date": "",
  "xml_id": "stock_dropshipping.field_stock_move__display_name"
}
