{
  "exported_at": "2026-05-11T13:09:28Z",
  "id": 19703,
  "model": "ir.model.fields",
  "payload": {
    "field_description": "Value Label",
    "model_id": [
      921,
      "Survey Label"
    ],
    "name": "value_label",
    "relation": false,
    "required": false,
    "state": "base",
    "store": false,
    "translate": false,
    "ttype": "char"
  },
  "payload_sha256": "4d1b299805930d5b67214d2233803141ffa044ee1e7d60b18c5f8d677589bb71",
  "write_date": "",
  "xml_id": "survey.field_survey_question_answer__value_label"
}
