{
  "exported_at": "2026-05-10T12:35:47Z",
  "id": 10031,
  "model": "ir.model.fields",
  "payload": {
    "field_description": "Action",
    "model_id": [
      688,
      "Website rewrite"
    ],
    "name": "redirect_type",
    "relation": false,
    "required": false,
    "state": "base",
    "store": true,
    "translate": false,
    "ttype": "selection"
  },
  "payload_sha256": "1f90eca031c9f96f633117f10a20e0e9ba02c904a80f145dc826d1ab29f1f2cd",
  "write_date": "",
  "xml_id": "website.field_website_rewrite__redirect_type"
}
