{
  "exported_at": "2026-05-11T13:09:28Z",
  "id": 14883,
  "model": "ir.model.fields",
  "payload": {
    "field_description": "Display Name",
    "model_id": [
      922,
      "Survey User Input"
    ],
    "name": "display_name",
    "relation": false,
    "required": false,
    "state": "base",
    "store": false,
    "translate": false,
    "ttype": "char"
  },
  "payload_sha256": "5173c895ccc117b29dbad14a8da58cc235fae7be92c5624ab482e8741f568aa7",
  "write_date": "",
  "xml_id": "website_slides_survey.field_survey_user_input__display_name"
}
